LICENSE
MANIFEST.in
README.ja.md
README.md
setup.cfg
setup.py
sitcpy/__init__.py
sitcpy/command.py
sitcpy/cui.py
sitcpy/daq_client.py
sitcpy/rbcp.py
sitcpy/rbcp_server.py
sitcpy.egg-info/PKG-INFO
sitcpy.egg-info/SOURCES.txt
sitcpy.egg-info/dependency_links.txt
sitcpy.egg-info/entry_points.txt
sitcpy.egg-info/top_level.txt
sitcpy/templates/__init__.py
sitcpy/templates/cui_project/__init__.py
sitcpy/templates/cui_project/config.json
sitcpy/templates/cui_project/daq.py
sitcpy/templates/cui_project/pseudo.py
sitcpy/templates/cui_project/templates.txt
sitcpy/templates/cui_project/vm_init/0.bin